SPI/CMAC/testbench/LSFR_2.v
module LSFR_2 (
  input  wire          load,
  input  wire          loadIt,
  input  wire          enable,
  output wire          newBit,
  input  wire          clk,
  input  wire          reset
);

  wire       [88:0]   fsRegN;
  reg        [88:0]   fsReg;
  wire                taps_0;
  wire                taps_1;
  reg                 genBit;

  assign taps_0 = fsReg[0];
  assign taps_1 = fsReg[51];
  always @(*) begin
    genBit = (taps_0 ^ taps_1);
    if(loadIt) begin
      genBit = load;
    end
  end

  assign newBit = fsReg[0];
  assign fsRegN = {genBit,fsReg[88 : 1]};
  always @(posedge clk) begin
    if(reset) begin
      fsReg <= 89'h0;
    end else begin
      if(enable) begin
        fsReg <= fsRegN;
      end
    end
  end


endmodule

SPI/CMAC/testbench/LSFR_1.v
module LSFR_1 (
  input  wire          load,
  input  wire          loadIt,
  input  wire          enable,
  output wire          newBit,
  input  wire          clk,
  input  wire          reset
);

  wire       [126:0]  fsRegN;
  reg        [126:0]  fsReg;
  wire                taps_0;
  wire                taps_1;
  reg                 genBit;

  assign taps_0 = fsReg[0];
  assign taps_1 = fsReg[126];
  always @(*) begin
    genBit = (taps_0 ^ taps_1);
    if(loadIt) begin
      genBit = load;
    end
  end

  assign newBit = fsReg[0];
  assign fsRegN = {genBit,fsReg[126 : 1]};
  always @(posedge clk) begin
    if(reset) begin
      fsReg <= 127'h0;
    end else begin
      if(enable) begin
        fsReg <= fsRegN;
      end
    end
  end


endmodule

SPI/CMAC/testbench/LSFR.v
module LSFR (
  input  wire          load,
  input  wire          loadIt,
  input  wire          enable,
  output wire          newBit,
  input  wire          clk,
  input  wire          reset
);

  wire       [30:0]   fsRegN;
  reg        [30:0]   fsReg;
  wire                taps_0;
  wire                taps_1;
  reg                 genBit;

  assign taps_0 = fsReg[0];
  assign taps_1 = fsReg[28];
  always @(*) begin
    genBit = (taps_0 ^ taps_1);
    if(loadIt) begin
      genBit = load;
    end
  end

  assign newBit = fsReg[0];
  assign fsRegN = {genBit,fsReg[30 : 1]};
  always @(posedge clk) begin
    if(reset) begin
      fsReg <= 31'h0;
    end else begin
      if(enable) begin
        fsReg <= fsRegN;
      end
    end
  end


endmodule

SPI/CMAC/testbench/ASG.v
`include "LSFR_2.v"
`include "LSFR_1.v"
`include "LSFR.v"



module ASG (
  input  wire [1:0]    loadIt,
  input  wire          load,
  input  wire          enable,
  output wire          newBit,
  input  wire          clk,
  input  wire          reset
);

  wire                R1_enable;
  wire                R2_enable;
  wire                R3_enable;
  wire                R1_newBit;
  wire                R2_newBit;
  wire                R3_newBit;
  wire                loadR1;
  wire                loadR2;
  wire                loadR3;

  LSFR R1 (
    .load   (load     ), //i
    .loadIt (loadR1   ), //i
    .enable (R1_enable), //i
    .newBit (R1_newBit), //o
    .clk    (clk      ), //i
    .reset  (reset    )  //i
  );
  LSFR_1 R2 (
    .load   (load     ), //i
    .loadIt (loadR2   ), //i
    .enable (R2_enable), //i
    .newBit (R2_newBit), //o
    .clk    (clk      ), //i
    .reset  (reset    )  //i
  );
  LSFR_2 R3 (
    .load   (load     ), //i
    .loadIt (loadR3   ), //i
    .enable (R3_enable), //i
    .newBit (R3_newBit), //o
    .clk    (clk      ), //i
    .reset  (reset    )  //i
  );
  assign loadR1 = (loadIt == 2'b01);
  assign loadR2 = (loadIt == 2'b10);
  assign loadR3 = (loadIt == 2'b11);
  assign R1_enable = (enable || loadR1);
  assign R2_enable = ((enable && R1_newBit) || loadR2);
  assign R3_enable = ((enable && (! R1_newBit)) || loadR3);
  assign newBit = (R2_newBit ^ R3_newBit);

endmodule

SPI/CMAC/testbench/testbench.sv
// Code your testbench here
// or browse Examples

`include "ASG.v"
`timescale 1ns/1ps

module ASG_TESTING ();
  
    // Intialize ASG variables
    wire [1:0] loadIt = 2'b0;
    wire       load;
    wire       enable = 1'b1;
    wire       newBit = 1'b0;  // ASG output
    logic      clk = 1'b0;
    wire       reset = 1'b0;
  
    // Clock Generators:
  always #(2) clk = ~clk;

    ASG asg1 (
        loadIt,
        load,
        enable,
        newBit,
        clk,
        reset
    );
  logic [5:0] count; // 6 Bit counter: 0..63 
  logic [63:0] own_challenge = 6'b0;
  logic sampling = 1'b0;
  logic sampled_done = 1'b0;
  logic enable_sample = 1'b1;
  
    task gen_bit();
      @(posedge clk);
      own_challenge <= {own_challenge[62:0], newBit};
    endtask
  
  	always_ff @(posedge clk) 
        begin 
            if (reset) 
                begin 
                    sampling <= 1'b0; 
                    count <= 6'd0; 
                    own_challenge <= 64'h0; 
                    sampled_done <= 1'b0; 
                end 
            else 
                begin 
                    if (!sampling) 
                        begin 
                            sampled_done <= 1'b0; 
                                if (enable_sample) 
                                    begin 
                                        sampling <= 1'b1; 
                                        count <= 6'd0; 
                                        own_challenge <= 64'h0; // initialize on zeros
                                    end 
                        end 
                    else // sampling == 1 
                        begin
                            // shift and collect
                            own_challenge <= {own_challenge[62:0], newBit};
                            // Alternative MSB-first: own_challenge <= {newBit, own_challenge[63:1]};
                            if (count == 6'd63) 
                                begin
                                    sampling     <= 1'b0;
                                    sampled_done <= 1'b1;
                                    count        <= 6'd0;
                                end
                            else
                                begin
                                    count <= count + 6'd1;
                                end
                        end
                end
        end
  
    initial
    begin
      // Required for EDA Playground
      $dumpfile("dump.vcd"); 
      $dumpvars;
      
      repeat(64) @(posedge clk);

      
      
      // Test generating pseudo random bits
      //gen_bit();
      //$display("first bit, Received 0x%X", own_challenge); 
      //repeat(10) @(posedge clk);
      //gen_bit();
      $display("?, Received 0x%X", own_challenge); 
      $finish();      
    end

endmodule

SPI/CMAC/testbench/dump.vcd
$date
	Sat Feb 28 00:32:14 2026
$end
$version
	Icarus Verilog
$end
$timescale
	1ps
$end
$scope module ASG_TESTING $end
$var wire 1 ! newBit $end
$var reg 1 " clk $end
$var reg 6 # count [5:0] $end
$var reg 1 $ enable $end
$var reg 1 % enable_sample $end
$var reg 1 & load $end
$var reg 2 ' loadIt [1:0] $end
$var reg 64 ( own_challenge [63:0] $end
$var reg 1 ) reset $end
$var reg 1 * sampled_done $end
$var reg 1 + sampling $end
$scope module asg1 $end
$var wire 1 , R1_enable $end
$var wire 1 - R2_enable $end
$var wire 1 . R3_enable $end
$var wire 1 " clk $end
$var wire 1 $ enable $end
$var wire 1 & load $end
$var wire 2 / loadIt [1:0] $end
$var wire 1 ! newBit $end
$var wire 1 ) reset $end
$var wire 1 0 loadR3 $end
$var wire 1 1 loadR2 $end
$var wire 1 2 loadR1 $end
$var wire 1 3 R3_newBit $end
$var wire 1 4 R2_newBit $end
$var wire 1 5 R1_newBit $end
$scope module R1 $end
$var wire 1 " clk $end
$var wire 1 , enable $end
$var wire 1 & load $end
$var wire 1 2 loadIt $end
$var wire 1 ) reset $end
$var wire 1 6 taps_1 $end
$var wire 1 7 taps_0 $end
$var wire 1 5 newBit $end
$var wire 31 8 fsRegN [30:0] $end
$var reg 31 9 fsReg [30:0] $end
$var reg 1 : genBit $end
$upscope $end
$scope module R2 $end
$var wire 1 " clk $end
$var wire 1 - enable $end
$var wire 1 & load $end
$var wire 1 1 loadIt $end
$var wire 1 ) reset $end
$var wire 1 ; taps_1 $end
$var wire 1 < taps_0 $end
$var wire 1 4 newBit $end
$var wire 127 = fsRegN [126:0] $end
$var reg 127 > fsReg [126:0] $end
$var reg 1 ? genBit $end
$upscope $end
$scope module R3 $end
$var wire 1 " clk $end
$var wire 1 . enable $end
$var wire 1 & load $end
$var wire 1 0 loadIt $end
$var wire 1 ) reset $end
$var wire 1 @ taps_1 $end
$var wire 1 A taps_0 $end
$var wire 1 3 newBit $end
$var wire 89 B fsRegN [88:0] $end
$var reg 89 C fsReg [88:0] $end
$var reg 1 D genBit $end
$upscope $end
$upscope $end
$upscope $end
$enddefinitions $end
$comment Show the parameter values. $end
$dumpall
$end
#0
$dumpvars
xD
bx C
bx B
xA
x@
x?
bx >
bx =
x<
x;
x:
bx 9
bx 8
x7
x6
x5
x4
x3
02
01
00
b0 /
x.
x-
1,
0+
0*
1)
b0 (
b0 '
0&
1%
1$
bx #
0"
x!
$end
#2000
1.
0-
0:
b0 8
0?
b0 =
0D
0!
b0 B
07
06
05
0<
0;
04
0A
0@
03
b0 9
b0 >
b0 C
0)
b0 #
1"
#4000
0"
#6000
1+
12
b1 '
b1 /
1"
#8000
0"
#10000
b1 #
1"
#12000
0"
#14000
b10 #
1"
#16000
0"
#18000
b11 #
1"
#20000
0"
#22000
b100 #
1"
#24000
0"
#26000
b101 #
1"
#28000
0"
#30000
b110 #
1"
#32000
0"
#34000
b111 #
1"
#36000
0"
#38000
b1000 #
1"
#40000
0"
#42000
b1001 #
1"
#44000
0"
#46000
b1010 #
1"
#48000
0"
#50000
b1011 #
1"
#52000
0"
#54000
b1100 #
1"
#56000
0"
#58000
b1101 #
1"
#60000
0"
#62000
b1110 #
1"
#64000
0"
#66000
b1111 #
1"
#68000
0"
#70000
b10000 #
1"
#72000
0"
#74000
b10001 #
1"
#76000
0"
#78000
b10010 #
1"
#80000
0"
#82000
b10011 #
1"
#84000
0"
#86000
b10100 #
1"
#88000
0"
#90000
b10101 #
1"
#92000
0"
#94000
b10110 #
1"
#96000
0"
#98000
b10111 #
1"
#100000
0"
#102000
b11000 #
1"
#104000
0"
#106000
b11001 #
1"
#108000
0"
#110000
b11010 #
1"
#112000
0"
#114000
b11011 #
1"
#116000
0"
#118000
b11100 #
1"
#120000
0"
#122000
b11101 #
1"
#124000
0"
#126000
b11110 #
1"
#128000
0"
#130000
b1000000000000000000000000000000 8
1:
1&
b11111 #
1"
#132000
0"
#134000
b100000000000000000000000000000 8
0:
b100000 #
0&
b1000000000000000000000000000000 9
1"
#136000
0"
#138000
b1010000000000000000000000000000 8
1:
b100000000000000000000000000000 9
1&
b100001 #
1"
#140000
0"
#142000
b1101000000000000000000000000000 8
16
b100010 #
b1010000000000000000000000000000 9
1"
#144000
0"
#146000
1:
b1110100000000000000000000000000 8
06
b1101000000000000000000000000000 9
b100011 #
1"
#148000
0"
#150000
b1111010000000000000000000000000 8
1-
16
b100100 #
0&
02
11
b10 '
b10 /
b1110100000000000000000000000000 9
1"
#152000
0"
#154000
b1111101000000000000000000000000 8
b1111010000000000000000000000000 9
b100101 #
1"
#156000
0"
#158000
b1111110100000000000000000000000 8
b100110 #
b1111101000000000000000000000000 9
1"
#160000
0"
#162000
b1111111010000000000000000000000 8
b1111110100000000000000000000000 9
b100111 #
1"
#164000
0"
#166000
b1111111101000000000000000000000 8
b101000 #
b1111111010000000000000000000000 9
1"
#168000
0"
#170000
b1111111110100000000000000000000 8
b1111111101000000000000000000000 9
b101001 #
1"
#172000
0"
#174000
b1111111111010000000000000000000 8
b101010 #
b1111111110100000000000000000000 9
1"
#176000
0"
#178000
b1111111111101000000000000000000 8
b1111111111010000000000000000000 9
b101011 #
1"
#180000
0"
#182000
b1111111111110100000000000000000 8
b101100 #
b1111111111101000000000000000000 9
1"
#184000
0"
#186000
b1111111111111010000000000000000 8
b1111111111110100000000000000000 9
b101101 #
1"
#188000
0"
#190000
b1111111111111101000000000000000 8
b101110 #
b1111111111111010000000000000000 9
1"
#192000
0"
#194000
b1111111111111110100000000000000 8
b1111111111111101000000000000000 9
b101111 #
1"
#196000
0"
#198000
b1111111111111111010000000000000 8
b110000 #
b1111111111111110100000000000000 9
1"
#200000
0"
#202000
b1111111111111111101000000000000 8
b1111111111111111010000000000000 9
b110001 #
1"
#204000
0"
#206000
b1111111111111111110100000000000 8
b110010 #
b1111111111111111101000000000000 9
1"
#208000
0"
#210000
b1111111111111111111010000000000 8
b1111111111111111110100000000000 9
b110011 #
1"
#212000
0"
#214000
b1111111111111111111101000000000 8
b110100 #
b1111111111111111111010000000000 9
1"
#216000
0"
#218000
b1111111111111111111110100000000 8
b1111111111111111111101000000000 9
b110101 #
1"
#220000
0"
#222000
b1111111111111111111111010000000 8
b110110 #
b1111111111111111111110100000000 9
1"
#224000
0"
#226000
b1111111111111111111111101000000 8
b1111111111111111111111010000000 9
b110111 #
1"
#228000
0"
#230000
b1111111111111111111111110100000 8
b111000 #
b1111111111111111111111101000000 9
1"
#232000
0"
#234000
b1111111111111111111111111010000 8
b1111111111111111111111110100000 9
b111001 #
1"
#236000
0"
#238000
b1111111111111111111111111101000 8
b111010 #
b1111111111111111111111111010000 9
1"
#240000
0"
#242000
b1111111111111111111111111110100 8
b1111111111111111111111111101000 9
b111011 #
1"
#244000
0"
#246000
b1111111111111111111111111111010 8
b111100 #
b1111111111111111111111111110100 9
1"
#248000
0"
#250000
b1111111111111111111111111111101 8
b1111111111111111111111111111010 9
b111101 #
1"
#252000
0"
#254000
0.
0:
b111111111111111111111111111110 8
17
15
b111110 #
b1111111111111111111111111111101 9
1"
#256000
0"
#258000
1.
1:
b1011111111111111111111111111111 8
07
05
b111111111111111111111111111110 9
b111111 #
1"
#260000
0"
#262000
0.
0:
b101111111111111111111111111111 8
17
15
b0 #
1*
0+
b1011111111111111111111111111111 9
1"
#264000
0"
#266000
1:
b1010111111111111111111111111111 8
06
b101111111111111111111111111111 9
1+
0*
1"
#268000
0"
#270000
0:
b101011111111111111111111111111 8
16
b1 #
b1010111111111111111111111111111 9
1"
#272000
0"
#274000
1:
b1010101111111111111111111111111 8
06
b101011111111111111111111111111 9
b10 #
1"
#276000
0"
#278000
0:
b101010111111111111111111111111 8
16
b11 #
b1010101111111111111111111111111 9
1"
#280000
0"
#282000
1:
b1010101011111111111111111111111 8
06
b101010111111111111111111111111 9
b100 #
1"
#284000
0"
#286000
0:
b101010101111111111111111111111 8
16
b101 #
b1010101011111111111111111111111 9
1"
#288000
0"
#290000
1:
b1010101010111111111111111111111 8
06
b101010101111111111111111111111 9
b110 #
1"
#292000
0"
#294000
0:
b101010101011111111111111111111 8
16
b111 #
b1010101010111111111111111111111 9
1"
#296000
0"
#298000
1:
b1010101010101111111111111111111 8
06
b101010101011111111111111111111 9
b1000 #
1"
#300000
0"
#302000
0:
b101010101010111111111111111111 8
16
b1001 #
b1010101010101111111111111111111 9
1"
#304000
0"
#306000
1:
b1010101010101011111111111111111 8
06
b101010101010111111111111111111 9
b1010 #
1"
#308000
0"
#310000
0:
b101010101010101111111111111111 8
16
b1011 #
b1010101010101011111111111111111 9
1"
#312000
0"
#314000
1:
b1010101010101010111111111111111 8
06
b101010101010101111111111111111 9
b1100 #
1"
#316000
0"
#318000
0:
b101010101010101011111111111111 8
16
b1101 #
b1010101010101010111111111111111 9
1"
#320000
0"
#322000
1:
b1010101010101010101111111111111 8
06
b101010101010101011111111111111 9
b1110 #
1"
#324000
0"
#326000
0:
b101010101010101010111111111111 8
16
b1111 #
b1010101010101010101111111111111 9
1"
#328000
0"
#330000
1:
b1010101010101010101011111111111 8
06
b101010101010101010111111111111 9
b10000 #
1"
#332000
0"
#334000
0:
b101010101010101010101111111111 8
16
b10001 #
b1010101010101010101011111111111 9
1"
#336000
0"
#338000
1:
b1010101010101010101010111111111 8
06
b101010101010101010101111111111 9
b10010 #
1"
#340000
0"
#342000
0:
b101010101010101010101011111111 8
16
b10011 #
b1010101010101010101010111111111 9
1"
#344000
0"
#346000
1:
b1010101010101010101010101111111 8
06
b101010101010101010101011111111 9
b10100 #
1"
#348000
0"
#350000
0:
b101010101010101010101010111111 8
16
b10101 #
b1010101010101010101010101111111 9
1"
#352000
0"
#354000
1:
b1010101010101010101010101011111 8
06
b101010101010101010101010111111 9
b10110 #
1"
#356000
0"
#358000
0:
b101010101010101010101010101111 8
16
b10111 #
b1010101010101010101010101011111 9
1"
#360000
0"
#362000
1:
b1010101010101010101010101010111 8
06
b101010101010101010101010101111 9
b11000 #
1"
#364000
0"
#366000
0:
b101010101010101010101010101011 8
16
b11001 #
b1010101010101010101010101010111 9
1"
#368000
0"
#370000
1:
b1010101010101010101010101010101 8
06
b101010101010101010101010101011 9
b11010 #
1"
#372000
0"
#374000
0:
b101010101010101010101010101010 8
16
b11011 #
b1010101010101010101010101010101 9
1"
#376000
0"
#378000
1.
b10101010101010101010101010101 8
07
06
05
b101010101010101010101010101010 9
b11100 #
1"
#380000
0"
#382000
0.
b1010101010101010101010101010 8
17
16
15
b11101 #
b10101010101010101010101010101 9
1"
#384000
0"
#386000
1.
b101010101010101010101010101 8
07
06
05
b1010101010101010101010101010 9
b11110 #
1"
#388000
0"
#390000
0.
1:
b1000010101010101010101010101010 8
17
15
b11111 #
b101010101010101010101010101 9
1"
#392000
0"
#394000
1.
0:
b100001010101010101010101010101 8
07
05
b1000010101010101010101010101010 9
b100000 #
1"
#396000
0"
#398000
0.
1:
b1010000101010101010101010101010 8
17
15
b100001 #
b100001010101010101010101010101 9
1"
#400000
0"
#402000
1.
b1101000010101010101010101010101 8
07
16
05
b1010000101010101010101010101010 9
b100010 #
1"
#404000
0"
#406000
0.
b1110100001010101010101010101010 8
17
06
15
b100011 #
b1101000010101010101010101010101 9
1"
#408000
0"
#410000
1.
b1111010000101010101010101010101 8
07
16
05
b1110100001010101010101010101010 9
b100100 #
1"
#412000
0"
#414000
0.
0:
b111101000010101010101010101010 8
17
15
b100101 #
b1111010000101010101010101010101 9
1"
#416000
0"
#418000
1.
1:
b1011110100001010101010101010101 8
07
05
b111101000010101010101010101010 9
b100110 #
1"
#420000
0"
#422000
0.
0:
b101111010000101010101010101010 8
17
15
b100111 #
b1011110100001010101010101010101 9
1"
#424000
0"
#426000
1.
b10111101000010101010101010101 8
07
06
05
b101111010000101010101010101010 9
b101000 #
1"
#428000
0"
#430000
0.
b1011110100001010101010101010 8
17
16
15
b101001 #
b10111101000010101010101010101 9
1"
#432000
0"
#434000
1.
b101111010000101010101010101 8
07
06
05
b1011110100001010101010101010 9
b101010 #
1"
#436000
0"
#438000
0.
1:
b1000010111101000010101010101010 8
17
15
b101011 #
b101111010000101010101010101 9
1"
#440000
0"
#442000
1.
0:
b100001011110100001010101010101 8
07
05
b1000010111101000010101010101010 9
b101100 #
1"
#444000
0"
#446000
0.
1:
b1010000101111010000101010101010 8
17
15
b101101 #
b100001011110100001010101010101 9
1"
#448000
0"
#450000
1.
b1101000010111101000010101010101 8
07
16
05
b1010000101111010000101010101010 9
b101110 #
1"
#452000
0"
#454000
0.
b1110100001011110100001010101010 8
17
06
15
b101111 #
b1101000010111101000010101010101 9
1"
#456000
0"
#458000
1.
b1111010000101111010000101010101 8
07
16
05
b1110100001011110100001010101010 9
b110000 #
1"
#460000
0"
#462000
0.
0:
b111101000010111101000010101010 8
17
15
b110001 #
b1111010000101111010000101010101 9
1"
#464000
0"
#466000
1.
1:
b1011110100001011110100001010101 8
07
05
b111101000010111101000010101010 9
b110010 #
1"
#468000
0"
#470000
0.
0:
b101111010000101111010000101010 8
17
15
b110011 #
b1011110100001011110100001010101 9
1"
#472000
0"
#474000
1.
b10111101000010111101000010101 8
07
06
05
b101111010000101111010000101010 9
b110100 #
1"
#476000
0"
#478000
0.
b1011110100001011110100001010 8
17
16
15
b110101 #
b10111101000010111101000010101 9
1"
#480000
0"
#482000
1.
b101111010000101111010000101 8
07
06
05
b1011110100001011110100001010 9
b110110 #
1"
#484000
0"
#486000
0.
1:
b1000010111101000010111101000010 8
17
15
b110111 #
b101111010000101111010000101 9
1"
#488000
0"
#490000
1.
0:
b100001011110100001011110100001 8
07
05
b1000010111101000010111101000010 9
b111000 #
1"
#492000
0"
#494000
0.
1:
b1010000101111010000101111010000 8
17
15
b111001 #
b100001011110100001011110100001 9
1"
#496000
0"
#498000
1.
b1101000010111101000010111101000 8
07
16
05
b1010000101111010000101111010000 9
b111010 #
1"
#500000
0"
#502000
0:
b110100001011110100001011110100 8
06
b111011 #
b1101000010111101000010111101000 9
1"
#504000
0"
#506000
1:
b1011010000101111010000101111010 8
16
b110100001011110100001011110100 9
b111100 #
1"
#508000
0"
#510000
b1101101000010111101000010111101 8
b111101 #
b1011010000101111010000101111010 9
1"
#512000
0"
#514000
0.
b1110110100001011110100001011110 8
17
06
15
b1101101000010111101000010111101 9
b111110 #
1"
#516000
0"
#518000
1.
b1111011010000101111010000101111 8
07
16
05
b111111 #
b1110110100001011110100001011110 9
1"
#520000
0"
#522000
0.
0:
b111101101000010111101000010111 8
17
15
b1111011010000101111010000101111 9
b0 #
1*
0+
1"
#524000
0"
#526000
b11110110100001011110100001011 8
1+
0*
b111101101000010111101000010111 9
1"
#528000
0"
#530000
b1111011010000101111010000101 8
b11110110100001011110100001011 9
b1 #
1"
#532000
0"
#534000
1:
b1000111101101000010111101000010 8
06
b10 #
b1111011010000101111010000101 9
1"
#536000
0"
#538000
1.
0:
b100011110110100001011110100001 8
07
05
b1000111101101000010111101000010 9
b11 #
1"
#540000
0"
#542000
0.
1:
b1010001111011010000101111010000 8
17
15
b100 #
b100011110110100001011110100001 9
1"
#544000
0"
#546000
1.
b1101000111101101000010111101000 8
07
16
05
b1010001111011010000101111010000 9
b101 #
1"
#548000
0"
#550000
0:
b110100011110110100001011110100 8
06
b110 #
b1101000111101101000010111101000 9
1"
#552000
0"
#554000
1:
b1011010001111011010000101111010 8
16
b110100011110110100001011110100 9
b111 #
1"
#556000
0"
#558000
b1101101000111101101000010111101 8
b1000 #
b1011010001111011010000101111010 9
1"
#560000
0"
#562000
0.
b1110110100011110110100001011110 8
17
06
15
b1101101000111101101000010111101 9
b1001 #
1"
#564000
0"
#566000
1.
b1111011010001111011010000101111 8
07
16
05
b1010 #
b1110110100011110110100001011110 9
1"
#568000
0"
#570000
0.
0:
b111101101000111101101000010111 8
17
15
b1111011010001111011010000101111 9
b1011 #
1"
#572000
0"
#574000
b11110110100011110110100001011 8
b1100 #
b111101101000111101101000010111 9
1"
#576000
0"
#578000
b1111011010001111011010000101 8
b11110110100011110110100001011 9
b1101 #
1"
#580000
0"
#582000
1:
b1000111101101000111101101000010 8
06
b1110 #
b1111011010001111011010000101 9
1"
#584000
0"
#586000
1.
0:
b100011110110100011110110100001 8
07
05
b1000111101101000111101101000010 9
b1111 #
1"
#588000
0"
#590000
0.
1:
b1010001111011010001111011010000 8
17
15
b10000 #
b100011110110100011110110100001 9
1"
#592000
0"
#594000
1.
b1101000111101101000111101101000 8
07
16
05
b1010001111011010001111011010000 9
b10001 #
1"
#596000
0"
#598000
0:
b110100011110110100011110110100 8
06
b10010 #
b1101000111101101000111101101000 9
1"
#600000
0"
#602000
1:
b1011010001111011010001111011010 8
16
b110100011110110100011110110100 9
b10011 #
1"
#604000
0"
#606000
b1101101000111101101000111101101 8
b10100 #
b1011010001111011010001111011010 9
1"
#608000
0"
#610000
0.
b1110110100011110110100011110110 8
17
06
15
b1101101000111101101000111101101 9
b10101 #
1"
#612000
0"
#614000
1.
b1111011010001111011010001111011 8
07
16
05
b10110 #
b1110110100011110110100011110110 9
1"
#616000
0"
#618000
0.
0:
b111101101000111101101000111101 8
17
15
b1111011010001111011010001111011 9
b10111 #
1"
#620000
0"
#622000
b11110110100011110110100011110 8
b11000 #
b111101101000111101101000111101 9
1"
#624000
0"
#626000
1.
1:
b1001111011010001111011010001111 8
07
05
b11110110100011110110100011110 9
b11001 #
1"
#628000
0"
#630000
0.
b1100111101101000111101101000111 8
17
06
15
b11010 #
b1001111011010001111011010001111 9
1"
#632000
0"
#634000
b1110011110110100011110110100011 8
b1100111101101000111101101000111 9
b11011 #
1"
#636000
0"
#638000
0:
b111001111011010001111011010001 8
16
b11100 #
b1110011110110100011110110100011 9
1"
#640000
0"
#642000
b11100111101101000111101101000 8
b111001111011010001111011010001 9
b11101 #
1"
#644000
0"
#646000
1.
1:
b1001110011110110100011110110100 8
07
05
b11110 #
b11100111101101000111101101000 9
1"
#648000
0"
#650000
0:
b100111001111011010001111011010 8
06
b1001110011110110100011110110100 9
b11111 #
1"
#652000
0"
#654000
b10011100111101101000111101101 8
b100000 #
b100111001111011010001111011010 9
1"
#656000
0"
#658000
0.
b1001110011110110100011110110 8
17
16
15
b10011100111101101000111101101 9
b100001 #
1"
#660000
0"
#662000
1.
b1000000000000000000000000000000000000000000000000000000000000000000000000000000000000000000000000000000000000000000000000000000 =
b100111001111011010001111011 8
1?
07
06
05
b100010 #
1&
b1001110011110110100011110110 9
1"
#664000
0"
#666000
0.
1:
b1000010011100111101101000111101 8
b100000000000000000000000000000000000000000000000000000000000000000000000000000000000000000000000000000000000000000000000000000 =
17
15
1;
0?
b100111001111011010001111011 9
b1000000000000000000000000000000000000000000000000000000000000000000000000000000000000000000000000000000000000000000000000000000 >
0&
b100011 #
1"
#668000
0"
#670000
b1010000000000000000000000000000000000000000000000000000000000000000000000000000000000000000000000000000000000000000000000000000 =
b1100001001110011110110100011110 8
1?
0;
b100100 #
1&
b100000000000000000000000000000000000000000000000000000000000000000000000000000000000000000000000000000000000000000000000000000 >
b1000010011100111101101000111101 9
1"
#672000
0"
#674000
1.
0:
b110000100111001111011010001111 8
b1101000000000000000000000000000000000000000000000000000000000000000000000000000000000000000000000000000000000000000000000000000 =
07
05
1;
b1100001001110011110110100011110 9
b1010000000000000000000000000000000000000000000000000000000000000000000000000000000000000000000000000000000000000000000000000000 >
b100101 #
1"
#676000
0"
#678000
b10000000000000000000000000000000000000000000000000000000000000000000000000000000000000000 B
b1110100000000000000000000000000000000000000000000000000000000000000000000000000000000000000000000000000000000000000000000000000 =
b11000010011100111101101000111 8
1-
1D
17
16
15
b100110 #
01
10
b11 '
b11 /
b1101000000000000000000000000000000000000000000000000000000000000000000000000000000000000000000000000000000000000000000000000000 >
b110000100111001111011010001111 9
1"
#680000
0"
#682000
b1100001001110011110110100011 8
b1111010000000000000000000000000000000000000000000000000000000000000000000000000000000000000000000000000000000000000000000000000 =
b11000000000000000000000000000000000000000000000000000000000000000000000000000000000000000 B
b11000010011100111101101000111 9
b1110100000000000000000000000000000000000000000000000000000000000000000000000000000000000000000000000000000000000000000000000000 >
b10000000000000000000000000000000000000000000000000000000000000000000000000000000000000000 C
b100111 #
1"
#684000
0"
#686000
b11100000000000000000000000000000000000000000000000000000000000000000000000000000000000000 B
b1111101000000000000000000000000000000000000000000000000000000000000000000000000000000000000000000000000000000000000000000000000 =
1:
b1000110000100111001111011010001 8
06
b101000 #
b11000000000000000000000000000000000000000000000000000000000000000000000000000000000000000 C
b1111010000000000000000000000000000000000000000000000000000000000000000000000000000000000000000000000000000000000000000000000000 >
b1100001001110011110110100011 9
1"
#688000
0"
#690000
b1100011000010011100111101101000 8
b1111110100000000000000000000000000000000000000000000000000000000000000000000000000000000000000000000000000000000000000000000000 =
b11110000000000000000000000000000000000000000000000000000000000000000000000000000000000000 B
b1000110000100111001111011010001 9
b1111101000000000000000000000000000000000000000000000000000000000000000000000000000000000000000000000000000000000000000000000000 >
b11100000000000000000000000000000000000000000000000000000000000000000000000000000000000000 C
b101001 #
1"
#692000
0"
#694000
0-
b11111000000000000000000000000000000000000000000000000000000000000000000000000000000000000 B
b1111111010000000000000000000000000000000000000000000000000000000000000000000000000000000000000000000000000000000000000000000000 =
0:
b110001100001001110011110110100 8
07
05
b101010 #
b11110000000000000000000000000000000000000000000000000000000000000000000000000000000000000 C
b1111110100000000000000000000000000000000000000000000000000000000000000000000000000000000000000000000000000000000000000000000000 >
b1100011000010011100111101101000 9
1"
#696000
0"
#698000
1:
b1011000110000100111001111011010 8
b11111100000000000000000000000000000000000000000000000000000000000000000000000000000000000 B
16
b110001100001001110011110110100 9
b11111000000000000000000000000000000000000000000000000000000000000000000000000000000000000 C
b101011 #
1"
#700000
0"
#702000
b11111110000000000000000000000000000000000000000000000000000000000000000000000000000000000 B
b1101100011000010011100111101101 8
b101100 #
b11111100000000000000000000000000000000000000000000000000000000000000000000000000000000000 C
b1011000110000100111001111011010 9
1"
#704000
0"
#706000
1-
b1110110001100001001110011110110 8
b11111111000000000000000000000000000000000000000000000000000000000000000000000000000000000 B
17
06
15
b1101100011000010011100111101101 9
b11111110000000000000000000000000000000000000000000000000000000000000000000000000000000000 C
b101101 #
1"
#708000
0"
#710000
0-
b11111111100000000000000000000000000000000000000000000000000000000000000000000000000000000 B
b1111111101000000000000000000000000000000000000000000000000000000000000000000000000000000000000000000000000000000000000000000000 =
b1111011000110000100111001111011 8
07
16
05
b101110 #
b11111111000000000000000000000000000000000000000000000000000000000000000000000000000000000 C
b1111111010000000000000000000000000000000000000000000000000000000000000000000000000000000000000000000000000000000000000000000000 >
b1110110001100001001110011110110 9
1"
#712000
0"
#714000
1-
0:
b111101100011000010011100111101 8
b11111111110000000000000000000000000000000000000000000000000000000000000000000000000000000 B
17
15
b1111011000110000100111001111011 9
b11111111100000000000000000000000000000000000000000000000000000000000000000000000000000000 C
b101111 #
1"
#716000
0"
#718000
b11111111111000000000000000000000000000000000000000000000000000000000000000000000000000000 B
b1111111110100000000000000000000000000000000000000000000000000000000000000000000000000000000000000000000000000000000000000000000 =
b11110110001100001001110011110 8
b110000 #
b11111111110000000000000000000000000000000000000000000000000000000000000000000000000000000 C
b1111111101000000000000000000000000000000000000000000000000000000000000000000000000000000000000000000000000000000000000000000000 >
b111101100011000010011100111101 9
1"
#720000
0"
#722000
0-
1:
b1001111011000110000100111001111 8
b1111111111010000000000000000000000000000000000000000000000000000000000000000000000000000000000000000000000000000000000000000000 =
b11111111111100000000000000000000000000000000000000000000000000000000000000000000000000000 B
07
05
b11110110001100001001110011110 9
b1111111110100000000000000000000000000000000000000000000000000000000000000000000000000000000000000000000000000000000000000000000 >
b11111111111000000000000000000000000000000000000000000000000000000000000000000000000000000 C
b110001 #
1"
#724000
0"
#726000
1-
b11111111111110000000000000000000000000000000000000000000000000000000000000000000000000000 B
b1100111101100011000010011100111 8
17
06
15
b110010 #
b11111111111100000000000000000000000000000000000000000000000000000000000000000000000000000 C
b1001111011000110000100111001111 9
1"
#728000
0"
