Steuer-FSM/SteuerFSM.v
module SteuerFSM (
    input wire clk,
    input wire rst,
    input wire start,
    input wire [3:0] digit,
    input wire enter,
    input wire [2:0] op,
    output reg [7:0] result,
    output reg done
);

    parameter IDLE = 3'd0,
            INPUT_A = 3'd1,
            INPUT_B = 3'd2,
            OP_SELECT = 3'd3,
            CALC = 3'd4,
            RESULT = 3'd5;
    
    reg [2:0] state, next_state;
    reg [7:0] A, B;

    // Zustandsregister
    always @(posedge clk or posedge rst) begin
        if(rst)
            state <= IDLE;
        else
            state <= next_state;
    end

    // Übergangslogik
    always @(*) begin
        next_state = state;
        case (state)
            IDLE: if(start) next_state = INPUT_A;
            INPUT_A: if(enter) next_state = INPUT_B;
            INPUT_B: if(enter) next_state = OP_SELECT;
            OP_SELECT: next_state = CALC;
            CALC:  next_state = RESULT;
            RESULT: next_state = IDLE;
        endcase
    end

    // Speicherung
    always @(posedge clk) begin
        if(state == INPUT_A && enter)
            A <= digit;
        else if(state == INPUT_B && enter)
            B <= digit;
    end

    //Berechnung
    always @(*) begin
        result = 0;
        done = 0;
        case (state)
            CALC: begin
                case (op)
                    3'b000: result = A + B;
                    3'b001: result = A - B;
                    3'b010: result = A & B;
                    3'b011: result = A | B;
                    3'b100: result = A * B;
                    3'b101: result = A / B;
                    default: result = (B!=0) ? A / B : 8'hFF; //Div durch 0
                endcase
            end
            RESULT: begin
                done = 1;
            end 
        endcase
    end
endmodule

Steuer-FSM/tb_SteuerFSM.v
`timescale 1ns/1ps

module tb_SteuerFSM;
    reg clk, rst, start, enter;
    reg [3:0] digit;
    reg [2:0] op;
    wire [7:0] result;
    wire done;

    SteuerFSM uut (.clk(clk), .rst(rst), .start(start), .enter(enter), .digit(digit), .op(op), .result(result), .done(done));

    always #5 clk = ~clk;

    initial begin
        $dumpfile("steuerFsm.vcd");
        $dumpvars(0, tb_SteuerFSM);

        $monitor("t=%0t digit=%d op=%b result=%d done=%b", $time, digit, op, result, done);

        clk=0; rst=1; start=0; enter=0; digit=0; op=0;
        #12 rst=0;

        start=1; #10; start=0;
        digit=4; enter=1; #10; enter=0; #10;
        digit=3; enter=1; #10; enter=0; #10;
        op=3'b000; #10
        #20;

        $display("Result=%d done=%d", result, done);

        #10 $finish;
    end
endmodule

Steuer-FSM/steuerFsm.vcd
$date
	Sun Nov  9 13:02:26 2025
$end
$version
	Icarus Verilog
$end
$timescale
	1ps
$end
$scope module tb_SteuerFSM $end
$var wire 8 ! result [7:0] $end
$var wire 1 " done $end
$var reg 1 # clk $end
$var reg 4 $ digit [3:0] $end
$var reg 1 % enter $end
$var reg 3 & op [2:0] $end
$var reg 1 ' rst $end
$var reg 1 ( start $end
$scope module uut $end
$var wire 1 # clk $end
$var wire 4 ) digit [3:0] $end
$var wire 1 % enter $end
$var wire 3 * op [2:0] $end
$var wire 1 ' rst $end
$var wire 1 ( start $end
$var parameter 3 + CALC $end
$var parameter 3 , IDLE $end
$var parameter 3 - INPUT_A $end
$var parameter 3 . INPUT_B $end
$var parameter 3 / OP_SELECT $end
$var parameter 3 0 RESULT $end
$var reg 8 1 A [7:0] $end
$var reg 8 2 B [7:0] $end
$var reg 1 " done $end
$var reg 3 3 next_state [2:0] $end
$var reg 8 4 result [7:0] $end
$var reg 3 5 state [2:0] $end
$upscope $end
$upscope $end
$enddefinitions $end
$comment Show the parameter values. $end
$dumpall
b101 0
b11 /
b10 .
b1 -
b0 ,
b100 +
$end
#0
$dumpvars
b0 5
b0 4
b0 3
bx 2
bx 1
b0 *
b0 )
0(
1'
b0 &
0%
b0 $
0#
0"
b0 !
$end
#5000
1#
#10000
0#
#12000
b1 3
1(
0'
#15000
b1 5
1#
#20000
0#
#22000
b10 3
1%
b100 $
b100 )
0(
#25000
b11 3
b100 1
b10 5
1#
#30000
0#
#32000
b10 3
0%
#35000
1#
#40000
0#
#42000
b11 3
1%
b11 $
b11 )
#45000
b100 3
b11 2
b11 5
1#
#50000
0#
#52000
b100 3
0%
#55000
b111 !
b111 4
b101 3
b100 5
1#
#60000
0#
#65000
1"
b0 !
b0 4
b0 3
b101 5
1#
#70000
0#
#75000
0"
b0 5
1#
